numpy_to_image.cp36-win_amd64.pyd
tracking_c_tools.cp36-win_amd64.pyd
nuclitrack/CellTrackApp.py
nuclitrack/Graph.py
nuclitrack/Image_Display.py
nuclitrack/Image_widget.py
nuclitrack/Loading_tools.py
nuclitrack/Segmentation_tools.py
nuclitrack/Tracking_tools.py
nuclitrack/Training_tools.py
nuclitrack/__init__.py
nuclitrack/cmaps.py
nuclitrack-1.0.9.dist-info/DESCRIPTION.rst
nuclitrack-1.0.9.dist-info/METADATA
nuclitrack-1.0.9.dist-info/RECORD
nuclitrack-1.0.9.dist-info/WHEEL
nuclitrack-1.0.9.dist-info/metadata.json
nuclitrack-1.0.9.dist-info/top_level.txt
