Metadata-Version: 2.0
Name: nuclitrack
Version: 1.0.9
Summary: Nuclei tracking program
Home-page: UNKNOWN
Author: Sam Cooper
Author-email: sam@socooper.com
License: MIT
Platform: UNKNOWN
Requires-Dist: Cython
Requires-Dist: h5py
Requires-Dist: kivy
Requires-Dist: matplotlib
Requires-Dist: numpy
Requires-Dist: pygame
Requires-Dist: scikit-image
Requires-Dist: scikit-learn
Requires-Dist: scipy
